<annotation>
	<folder></folder>
	<filename>1478896569024419960_jpg.rf.9ce7ac11df15f4b3ab87559ce81f586e.jpg</filename>
	<path>1478896569024419960_jpg.rf.9ce7ac11df15f4b3ab87559ce81f586e.jpg</path>
	<source>
		<database>roboflow.ai</database>
	</source>
	<size>
		<width>416</width>
		<height>416</height>
		<depth>3</depth>
	</size>
	<segmented>0</segmented>
	<object>
		<name>car</name>
		<pose>Unspecified</pose>
		<truncated>0</truncated>
		<difficult>0</difficult>
		<occluded>0</occluded>
		<bndbox>
			<xmin>7</xmin>
			<xmax>61</xmax>
			<ymin>215</ymin>
			<ymax>241</ymax>
		</bndbox>
	</object>
	<object>
		<name>car</name>
		<pose>Unspecified</pose>
		<truncated>0</truncated>
		<difficult>0</difficult>
		<occluded>0</occluded>
		<bndbox>
			<xmin>169</xmin>
			<xmax>190</xmax>
			<ymin>202</ymin>
			<ymax>232</ymax>
		</bndbox>
	</object>
	<object>
		<name>car</name>
		<pose>Unspecified</pose>
		<truncated>0</truncated>
		<difficult>0</difficult>
		<occluded>0</occluded>
		<bndbox>
			<xmin>193</xmin>
			<xmax>214</xmax>
			<ymin>209</ymin>
			<ymax>227</ymax>
		</bndbox>
	</object>
</annotation>
