<annotation>
	<folder></folder>
	<filename>1478901169048630125_jpg.rf.7cea38bdd88f9b62138ac56e4f40253e.jpg</filename>
	<path>1478901169048630125_jpg.rf.7cea38bdd88f9b62138ac56e4f40253e.jpg</path>
	<source>
		<database>roboflow.ai</database>
	</source>
	<size>
		<width>416</width>
		<height>416</height>
		<depth>3</depth>
	</size>
	<segmented>0</segmented>
	<object>
		<name>car</name>
		<pose>Unspecified</pose>
		<truncated>0</truncated>
		<difficult>0</difficult>
		<occluded>0</occluded>
		<bndbox>
			<xmin>127</xmin>
			<xmax>132</xmax>
			<ymin>206</ymin>
			<ymax>211</ymax>
		</bndbox>
	</object>
	<object>
		<name>car</name>
		<pose>Unspecified</pose>
		<truncated>0</truncated>
		<difficult>0</difficult>
		<occluded>0</occluded>
		<bndbox>
			<xmin>145</xmin>
			<xmax>155</xmax>
			<ymin>201</ymin>
			<ymax>212</ymax>
		</bndbox>
	</object>
	<object>
		<name>car</name>
		<pose>Unspecified</pose>
		<truncated>0</truncated>
		<difficult>0</difficult>
		<occluded>0</occluded>
		<bndbox>
			<xmin>2</xmin>
			<xmax>25</xmax>
			<ymin>209</ymin>
			<ymax>282</ymax>
		</bndbox>
	</object>
</annotation>
