<annotation>
	<folder></folder>
	<filename>1478732263605199120_jpg.rf.af34b3bb197477c97456f204b5750678.jpg</filename>
	<path>1478732263605199120_jpg.rf.af34b3bb197477c97456f204b5750678.jpg</path>
	<source>
		<database>roboflow.ai</database>
	</source>
	<size>
		<width>416</width>
		<height>416</height>
		<depth>3</depth>
	</size>
	<segmented>0</segmented>
	<object>
		<name>car</name>
		<pose>Unspecified</pose>
		<truncated>0</truncated>
		<difficult>0</difficult>
		<occluded>0</occluded>
		<bndbox>
			<xmin>1</xmin>
			<xmax>126</xmax>
			<ymin>174</ymin>
			<ymax>317</ymax>
		</bndbox>
	</object>
	<object>
		<name>truck</name>
		<pose>Unspecified</pose>
		<truncated>0</truncated>
		<difficult>0</difficult>
		<occluded>0</occluded>
		<bndbox>
			<xmin>102</xmin>
			<xmax>131</xmax>
			<ymin>173</ymin>
			<ymax>222</ymax>
		</bndbox>
	</object>
	<object>
		<name>car</name>
		<pose>Unspecified</pose>
		<truncated>0</truncated>
		<difficult>0</difficult>
		<occluded>0</occluded>
		<bndbox>
			<xmin>132</xmin>
			<xmax>161</xmax>
			<ymin>184</ymin>
			<ymax>223</ymax>
		</bndbox>
	</object>
	<object>
		<name>trafficLight-RedLeft</name>
		<pose>Unspecified</pose>
		<truncated>0</truncated>
		<difficult>0</difficult>
		<occluded>0</occluded>
		<bndbox>
			<xmin>145</xmin>
			<xmax>153</xmax>
			<ymin>131</ymin>
			<ymax>153</ymax>
		</bndbox>
	</object>
	<object>
		<name>car</name>
		<pose>Unspecified</pose>
		<truncated>0</truncated>
		<difficult>0</difficult>
		<occluded>0</occluded>
		<bndbox>
			<xmin>157</xmin>
			<xmax>186</xmax>
			<ymin>197</ymin>
			<ymax>223</ymax>
		</bndbox>
	</object>
	<object>
		<name>trafficLight-Green</name>
		<pose>Unspecified</pose>
		<truncated>0</truncated>
		<difficult>0</difficult>
		<occluded>0</occluded>
		<bndbox>
			<xmin>181</xmin>
			<xmax>187</xmax>
			<ymin>137</ymin>
			<ymax>157</ymax>
		</bndbox>
	</object>
	<object>
		<name>car</name>
		<pose>Unspecified</pose>
		<truncated>0</truncated>
		<difficult>0</difficult>
		<occluded>0</occluded>
		<bndbox>
			<xmin>182</xmin>
			<xmax>200</xmax>
			<ymin>195</ymin>
			<ymax>221</ymax>
		</bndbox>
	</object>
	<object>
		<name>car</name>
		<pose>Unspecified</pose>
		<truncated>0</truncated>
		<difficult>0</difficult>
		<occluded>0</occluded>
		<bndbox>
			<xmin>196</xmin>
			<xmax>206</xmax>
			<ymin>195</ymin>
			<ymax>216</ymax>
		</bndbox>
	</object>
	<object>
		<name>trafficLight-Green</name>
		<pose>Unspecified</pose>
		<truncated>0</truncated>
		<difficult>0</difficult>
		<occluded>0</occluded>
		<bndbox>
			<xmin>203</xmin>
			<xmax>209</xmax>
			<ymin>139</ymin>
			<ymax>155</ymax>
		</bndbox>
	</object>
	<object>
		<name>car</name>
		<pose>Unspecified</pose>
		<truncated>0</truncated>
		<difficult>0</difficult>
		<occluded>0</occluded>
		<bndbox>
			<xmin>209</xmin>
			<xmax>223</xmax>
			<ymin>196</ymin>
			<ymax>213</ymax>
		</bndbox>
	</object>
	<object>
		<name>truck</name>
		<pose>Unspecified</pose>
		<truncated>0</truncated>
		<difficult>0</difficult>
		<occluded>0</occluded>
		<bndbox>
			<xmin>223</xmin>
			<xmax>235</xmax>
			<ymin>187</ymin>
			<ymax>207</ymax>
		</bndbox>
	</object>
	<object>
		<name>trafficLight-Green</name>
		<pose>Unspecified</pose>
		<truncated>0</truncated>
		<difficult>0</difficult>
		<occluded>0</occluded>
		<bndbox>
			<xmin>248</xmin>
			<xmax>255</xmax>
			<ymin>166</ymin>
			<ymax>184</ymax>
		</bndbox>
	</object>
	<object>
		<name>trafficLight-Green</name>
		<pose>Unspecified</pose>
		<truncated>0</truncated>
		<difficult>0</difficult>
		<occluded>0</occluded>
		<bndbox>
			<xmin>249</xmin>
			<xmax>255</xmax>
			<ymin>169</ymin>
			<ymax>184</ymax>
		</bndbox>
	</object>
	<object>
		<name>car</name>
		<pose>Unspecified</pose>
		<truncated>0</truncated>
		<difficult>0</difficult>
		<occluded>0</occluded>
		<bndbox>
			<xmin>257</xmin>
			<xmax>291</xmax>
			<ymin>195</ymin>
			<ymax>242</ymax>
		</bndbox>
	</object>
	<object>
		<name>trafficLight-Green</name>
		<pose>Unspecified</pose>
		<truncated>0</truncated>
		<difficult>0</difficult>
		<occluded>0</occluded>
		<bndbox>
			<xmin>267</xmin>
			<xmax>276</xmax>
			<ymin>157</ymin>
			<ymax>178</ymax>
		</bndbox>
	</object>
	<object>
		<name>trafficLight-Green</name>
		<pose>Unspecified</pose>
		<truncated>0</truncated>
		<difficult>0</difficult>
		<occluded>0</occluded>
		<bndbox>
			<xmin>268</xmin>
			<xmax>275</xmax>
			<ymin>152</ymin>
			<ymax>174</ymax>
		</bndbox>
	</object>
	<object>
		<name>car</name>
		<pose>Unspecified</pose>
		<truncated>0</truncated>
		<difficult>0</difficult>
		<occluded>0</occluded>
		<bndbox>
			<xmin>291</xmin>
			<xmax>327</xmax>
			<ymin>193</ymin>
			<ymax>213</ymax>
		</bndbox>
	</object>
</annotation>
