<annotation>
	<folder></folder>
	<filename>1478732597946249816_jpg.rf.4f8b984822b2af346e3b437ad979faa2.jpg</filename>
	<path>1478732597946249816_jpg.rf.4f8b984822b2af346e3b437ad979faa2.jpg</path>
	<source>
		<database>roboflow.ai</database>
	</source>
	<size>
		<width>416</width>
		<height>416</height>
		<depth>3</depth>
	</size>
	<segmented>0</segmented>
	<object>
		<name>car</name>
		<pose>Unspecified</pose>
		<truncated>0</truncated>
		<difficult>0</difficult>
		<occluded>0</occluded>
		<bndbox>
			<xmin>2</xmin>
			<xmax>58</xmax>
			<ymin>202</ymin>
			<ymax>268</ymax>
		</bndbox>
	</object>
	<object>
		<name>car</name>
		<pose>Unspecified</pose>
		<truncated>0</truncated>
		<difficult>0</difficult>
		<occluded>0</occluded>
		<bndbox>
			<xmin>53</xmin>
			<xmax>97</xmax>
			<ymin>207</ymin>
			<ymax>257</ymax>
		</bndbox>
	</object>
	<object>
		<name>car</name>
		<pose>Unspecified</pose>
		<truncated>0</truncated>
		<difficult>0</difficult>
		<occluded>0</occluded>
		<bndbox>
			<xmin>54</xmin>
			<xmax>94</xmax>
			<ymin>209</ymin>
			<ymax>248</ymax>
		</bndbox>
	</object>
	<object>
		<name>car</name>
		<pose>Unspecified</pose>
		<truncated>0</truncated>
		<difficult>0</difficult>
		<occluded>0</occluded>
		<bndbox>
			<xmin>95</xmin>
			<xmax>131</xmax>
			<ymin>201</ymin>
			<ymax>243</ymax>
		</bndbox>
	</object>
	<object>
		<name>car</name>
		<pose>Unspecified</pose>
		<truncated>0</truncated>
		<difficult>0</difficult>
		<occluded>0</occluded>
		<bndbox>
			<xmin>97</xmin>
			<xmax>126</xmax>
			<ymin>198</ymin>
			<ymax>236</ymax>
		</bndbox>
	</object>
	<object>
		<name>car</name>
		<pose>Unspecified</pose>
		<truncated>0</truncated>
		<difficult>0</difficult>
		<occluded>0</occluded>
		<bndbox>
			<xmin>124</xmin>
			<xmax>139</xmax>
			<ymin>204</ymin>
			<ymax>235</ymax>
		</bndbox>
	</object>
	<object>
		<name>car</name>
		<pose>Unspecified</pose>
		<truncated>0</truncated>
		<difficult>0</difficult>
		<occluded>0</occluded>
		<bndbox>
			<xmin>127</xmin>
			<xmax>141</xmax>
			<ymin>203</ymin>
			<ymax>235</ymax>
		</bndbox>
	</object>
	<object>
		<name>car</name>
		<pose>Unspecified</pose>
		<truncated>0</truncated>
		<difficult>0</difficult>
		<occluded>0</occluded>
		<bndbox>
			<xmin>135</xmin>
			<xmax>156</xmax>
			<ymin>201</ymin>
			<ymax>226</ymax>
		</bndbox>
	</object>
	<object>
		<name>car</name>
		<pose>Unspecified</pose>
		<truncated>0</truncated>
		<difficult>0</difficult>
		<occluded>0</occluded>
		<bndbox>
			<xmin>140</xmin>
			<xmax>157</xmax>
			<ymin>201</ymin>
			<ymax>229</ymax>
		</bndbox>
	</object>
	<object>
		<name>car</name>
		<pose>Unspecified</pose>
		<truncated>0</truncated>
		<difficult>0</difficult>
		<occluded>0</occluded>
		<bndbox>
			<xmin>194</xmin>
			<xmax>215</xmax>
			<ymin>194</ymin>
			<ymax>232</ymax>
		</bndbox>
	</object>
	<object>
		<name>car</name>
		<pose>Unspecified</pose>
		<truncated>0</truncated>
		<difficult>0</difficult>
		<occluded>0</occluded>
		<bndbox>
			<xmin>225</xmin>
			<xmax>234</xmax>
			<ymin>204</ymin>
			<ymax>229</ymax>
		</bndbox>
	</object>
	<object>
		<name>car</name>
		<pose>Unspecified</pose>
		<truncated>0</truncated>
		<difficult>0</difficult>
		<occluded>0</occluded>
		<bndbox>
			<xmin>228</xmin>
			<xmax>258</xmax>
			<ymin>199</ymin>
			<ymax>233</ymax>
		</bndbox>
	</object>
</annotation>
