<annotation>
	<folder></folder>
	<filename>1478020911212207355_jpg.rf.582c1ed05e3e749b2abb069dd7538eb8.jpg</filename>
	<path>1478020911212207355_jpg.rf.582c1ed05e3e749b2abb069dd7538eb8.jpg</path>
	<source>
		<database>roboflow.ai</database>
	</source>
	<size>
		<width>416</width>
		<height>416</height>
		<depth>3</depth>
	</size>
	<segmented>0</segmented>
	<object>
		<name>car</name>
		<pose>Unspecified</pose>
		<truncated>0</truncated>
		<difficult>0</difficult>
		<occluded>0</occluded>
		<bndbox>
			<xmin>1</xmin>
			<xmax>64</xmax>
			<ymin>194</ymin>
			<ymax>278</ymax>
		</bndbox>
	</object>
	<object>
		<name>car</name>
		<pose>Unspecified</pose>
		<truncated>0</truncated>
		<difficult>0</difficult>
		<occluded>0</occluded>
		<bndbox>
			<xmin>203</xmin>
			<xmax>219</xmax>
			<ymin>196</ymin>
			<ymax>219</ymax>
		</bndbox>
	</object>
	<object>
		<name>car</name>
		<pose>Unspecified</pose>
		<truncated>0</truncated>
		<difficult>0</difficult>
		<occluded>0</occluded>
		<bndbox>
			<xmin>224</xmin>
			<xmax>244</xmax>
			<ymin>196</ymin>
			<ymax>219</ymax>
		</bndbox>
	</object>
</annotation>
