<annotation>
	<folder></folder>
	<filename>1478899633993703282_jpg.rf.f03ce6f033af7c48178a2bafb5fde147.jpg</filename>
	<path>1478899633993703282_jpg.rf.f03ce6f033af7c48178a2bafb5fde147.jpg</path>
	<source>
		<database>roboflow.ai</database>
	</source>
	<size>
		<width>416</width>
		<height>416</height>
		<depth>3</depth>
	</size>
	<segmented>0</segmented>
	<object>
		<name>trafficLight-Red</name>
		<pose>Unspecified</pose>
		<truncated>0</truncated>
		<difficult>0</difficult>
		<occluded>0</occluded>
		<bndbox>
			<xmin>238</xmin>
			<xmax>249</xmax>
			<ymin>110</ymin>
			<ymax>147</ymax>
		</bndbox>
	</object>
	<object>
		<name>truck</name>
		<pose>Unspecified</pose>
		<truncated>0</truncated>
		<difficult>0</difficult>
		<occluded>0</occluded>
		<bndbox>
			<xmin>2</xmin>
			<xmax>270</xmax>
			<ymin>83</ymin>
			<ymax>312</ymax>
		</bndbox>
	</object>
	<object>
		<name>pedestrian</name>
		<pose>Unspecified</pose>
		<truncated>0</truncated>
		<difficult>0</difficult>
		<occluded>0</occluded>
		<bndbox>
			<xmin>302</xmin>
			<xmax>392</xmax>
			<ymin>105</ymin>
			<ymax>416</ymax>
		</bndbox>
	</object>
	<object>
		<name>pedestrian</name>
		<pose>Unspecified</pose>
		<truncated>0</truncated>
		<difficult>0</difficult>
		<occluded>0</occluded>
		<bndbox>
			<xmin>406</xmin>
			<xmax>416</xmax>
			<ymin>167</ymin>
			<ymax>231</ymax>
		</bndbox>
	</object>
</annotation>
