<annotation>
	<folder></folder>
	<filename>1478900508638548939_jpg.rf.978044cf822d9614b005a10e28d8a2ca.jpg</filename>
	<path>1478900508638548939_jpg.rf.978044cf822d9614b005a10e28d8a2ca.jpg</path>
	<source>
		<database>roboflow.ai</database>
	</source>
	<size>
		<width>416</width>
		<height>416</height>
		<depth>3</depth>
	</size>
	<segmented>0</segmented>
	<object>
		<name>car</name>
		<pose>Unspecified</pose>
		<truncated>0</truncated>
		<difficult>0</difficult>
		<occluded>0</occluded>
		<bndbox>
			<xmin>162</xmin>
			<xmax>172</xmax>
			<ymin>219</ymin>
			<ymax>231</ymax>
		</bndbox>
	</object>
	<object>
		<name>car</name>
		<pose>Unspecified</pose>
		<truncated>0</truncated>
		<difficult>0</difficult>
		<occluded>0</occluded>
		<bndbox>
			<xmin>1</xmin>
			<xmax>56</xmax>
			<ymin>198</ymin>
			<ymax>280</ymax>
		</bndbox>
	</object>
	<object>
		<name>car</name>
		<pose>Unspecified</pose>
		<truncated>0</truncated>
		<difficult>0</difficult>
		<occluded>0</occluded>
		<bndbox>
			<xmin>137</xmin>
			<xmax>152</xmax>
			<ymin>214</ymin>
			<ymax>236</ymax>
		</bndbox>
	</object>
	<object>
		<name>car</name>
		<pose>Unspecified</pose>
		<truncated>0</truncated>
		<difficult>0</difficult>
		<occluded>0</occluded>
		<bndbox>
			<xmin>176</xmin>
			<xmax>190</xmax>
			<ymin>210</ymin>
			<ymax>233</ymax>
		</bndbox>
	</object>
</annotation>
