<annotation>
	<folder></folder>
	<filename>1478896707847375404_jpg.rf.f6b1f6fb0f70e36865f254c9ad5272a5.jpg</filename>
	<path>1478896707847375404_jpg.rf.f6b1f6fb0f70e36865f254c9ad5272a5.jpg</path>
	<source>
		<database>roboflow.ai</database>
	</source>
	<size>
		<width>416</width>
		<height>416</height>
		<depth>3</depth>
	</size>
	<segmented>0</segmented>
	<object>
		<name>car</name>
		<pose>Unspecified</pose>
		<truncated>0</truncated>
		<difficult>0</difficult>
		<occluded>0</occluded>
		<bndbox>
			<xmin>70</xmin>
			<xmax>282</xmax>
			<ymin>159</ymin>
			<ymax>399</ymax>
		</bndbox>
	</object>
	<object>
		<name>car</name>
		<pose>Unspecified</pose>
		<truncated>0</truncated>
		<difficult>0</difficult>
		<occluded>0</occluded>
		<bndbox>
			<xmin>264</xmin>
			<xmax>294</xmax>
			<ymin>195</ymin>
			<ymax>224</ymax>
		</bndbox>
	</object>
	<object>
		<name>car</name>
		<pose>Unspecified</pose>
		<truncated>0</truncated>
		<difficult>0</difficult>
		<occluded>0</occluded>
		<bndbox>
			<xmin>267</xmin>
			<xmax>290</xmax>
			<ymin>197</ymin>
			<ymax>216</ymax>
		</bndbox>
	</object>
	<object>
		<name>trafficLight-Red</name>
		<pose>Unspecified</pose>
		<truncated>0</truncated>
		<difficult>0</difficult>
		<occluded>0</occluded>
		<bndbox>
			<xmin>310</xmin>
			<xmax>321</xmax>
			<ymin>91</ymin>
			<ymax>127</ymax>
		</bndbox>
	</object>
	<object>
		<name>car</name>
		<pose>Unspecified</pose>
		<truncated>0</truncated>
		<difficult>0</difficult>
		<occluded>0</occluded>
		<bndbox>
			<xmin>319</xmin>
			<xmax>342</xmax>
			<ymin>192</ymin>
			<ymax>216</ymax>
		</bndbox>
	</object>
	<object>
		<name>trafficLight-Red</name>
		<pose>Unspecified</pose>
		<truncated>0</truncated>
		<difficult>0</difficult>
		<occluded>0</occluded>
		<bndbox>
			<xmin>363</xmin>
			<xmax>372</xmax>
			<ymin>148</ymin>
			<ymax>175</ymax>
		</bndbox>
	</object>
	<object>
		<name>car</name>
		<pose>Unspecified</pose>
		<truncated>0</truncated>
		<difficult>0</difficult>
		<occluded>0</occluded>
		<bndbox>
			<xmin>396</xmin>
			<xmax>416</xmax>
			<ymin>212</ymin>
			<ymax>355</ymax>
		</bndbox>
	</object>
</annotation>
