<annotation>
	<folder></folder>
	<filename>1478900094452974982_jpg.rf.24473b1c195a3e01d0a1e0de81223ad8.jpg</filename>
	<path>1478900094452974982_jpg.rf.24473b1c195a3e01d0a1e0de81223ad8.jpg</path>
	<source>
		<database>roboflow.ai</database>
	</source>
	<size>
		<width>416</width>
		<height>416</height>
		<depth>3</depth>
	</size>
	<segmented>0</segmented>
	<object>
		<name>car</name>
		<pose>Unspecified</pose>
		<truncated>0</truncated>
		<difficult>0</difficult>
		<occluded>0</occluded>
		<bndbox>
			<xmin>364</xmin>
			<xmax>417</xmax>
			<ymin>183</ymin>
			<ymax>315</ymax>
		</bndbox>
	</object>
	<object>
		<name>truck</name>
		<pose>Unspecified</pose>
		<truncated>0</truncated>
		<difficult>0</difficult>
		<occluded>0</occluded>
		<bndbox>
			<xmin>368</xmin>
			<xmax>417</xmax>
			<ymin>121</ymin>
			<ymax>257</ymax>
		</bndbox>
	</object>
	<object>
		<name>car</name>
		<pose>Unspecified</pose>
		<truncated>0</truncated>
		<difficult>0</difficult>
		<occluded>0</occluded>
		<bndbox>
			<xmin>108</xmin>
			<xmax>124</xmax>
			<ymin>208</ymin>
			<ymax>229</ymax>
		</bndbox>
	</object>
</annotation>
