<annotation>
	<folder></folder>
	<filename>1478900741153208718_jpg.rf.4746b1268619a3496b184972e68d881d.jpg</filename>
	<path>1478900741153208718_jpg.rf.4746b1268619a3496b184972e68d881d.jpg</path>
	<source>
		<database>roboflow.ai</database>
	</source>
	<size>
		<width>416</width>
		<height>416</height>
		<depth>3</depth>
	</size>
	<segmented>0</segmented>
	<object>
		<name>car</name>
		<pose>Unspecified</pose>
		<truncated>0</truncated>
		<difficult>0</difficult>
		<occluded>0</occluded>
		<bndbox>
			<xmin>159</xmin>
			<xmax>171</xmax>
			<ymin>207</ymin>
			<ymax>231</ymax>
		</bndbox>
	</object>
	<object>
		<name>car</name>
		<pose>Unspecified</pose>
		<truncated>0</truncated>
		<difficult>0</difficult>
		<occluded>0</occluded>
		<bndbox>
			<xmin>98</xmin>
			<xmax>128</xmax>
			<ymin>208</ymin>
			<ymax>247</ymax>
		</bndbox>
	</object>
	<object>
		<name>pedestrian</name>
		<pose>Unspecified</pose>
		<truncated>0</truncated>
		<difficult>0</difficult>
		<occluded>0</occluded>
		<bndbox>
			<xmin>248</xmin>
			<xmax>259</xmax>
			<ymin>194</ymin>
			<ymax>229</ymax>
		</bndbox>
	</object>
</annotation>
