<annotation>
	<folder></folder>
	<filename>1478898314314775028_jpg.rf.20b21f85c35982b8bf9f0ee08c7014a0.jpg</filename>
	<path>1478898314314775028_jpg.rf.20b21f85c35982b8bf9f0ee08c7014a0.jpg</path>
	<source>
		<database>roboflow.ai</database>
	</source>
	<size>
		<width>416</width>
		<height>416</height>
		<depth>3</depth>
	</size>
	<segmented>0</segmented>
	<object>
		<name>biker</name>
		<pose>Unspecified</pose>
		<truncated>0</truncated>
		<difficult>0</difficult>
		<occluded>0</occluded>
		<bndbox>
			<xmin>315</xmin>
			<xmax>339</xmax>
			<ymin>199</ymin>
			<ymax>242</ymax>
		</bndbox>
	</object>
	<object>
		<name>car</name>
		<pose>Unspecified</pose>
		<truncated>0</truncated>
		<difficult>0</difficult>
		<occluded>0</occluded>
		<bndbox>
			<xmin>35</xmin>
			<xmax>68</xmax>
			<ymin>211</ymin>
			<ymax>240</ymax>
		</bndbox>
	</object>
	<object>
		<name>car</name>
		<pose>Unspecified</pose>
		<truncated>0</truncated>
		<difficult>0</difficult>
		<occluded>0</occluded>
		<bndbox>
			<xmin>39</xmin>
			<xmax>96</xmax>
			<ymin>206</ymin>
			<ymax>252</ymax>
		</bndbox>
	</object>
	<object>
		<name>car</name>
		<pose>Unspecified</pose>
		<truncated>0</truncated>
		<difficult>0</difficult>
		<occluded>0</occluded>
		<bndbox>
			<xmin>71</xmin>
			<xmax>206</xmax>
			<ymin>186</ymin>
			<ymax>357</ymax>
		</bndbox>
	</object>
	<object>
		<name>trafficLight-RedLeft</name>
		<pose>Unspecified</pose>
		<truncated>0</truncated>
		<difficult>0</difficult>
		<occluded>0</occluded>
		<bndbox>
			<xmin>114</xmin>
			<xmax>122</xmax>
			<ymin>104</ymin>
			<ymax>127</ymax>
		</bndbox>
	</object>
	<object>
		<name>trafficLight-Red</name>
		<pose>Unspecified</pose>
		<truncated>0</truncated>
		<difficult>0</difficult>
		<occluded>0</occluded>
		<bndbox>
			<xmin>161</xmin>
			<xmax>167</xmax>
			<ymin>108</ymin>
			<ymax>133</ymax>
		</bndbox>
	</object>
	<object>
		<name>pedestrian</name>
		<pose>Unspecified</pose>
		<truncated>0</truncated>
		<difficult>0</difficult>
		<occluded>0</occluded>
		<bndbox>
			<xmin>214</xmin>
			<xmax>219</xmax>
			<ymin>204</ymin>
			<ymax>232</ymax>
		</bndbox>
	</object>
	<object>
		<name>pedestrian</name>
		<pose>Unspecified</pose>
		<truncated>0</truncated>
		<difficult>0</difficult>
		<occluded>0</occluded>
		<bndbox>
			<xmin>218</xmin>
			<xmax>224</xmax>
			<ymin>206</ymin>
			<ymax>229</ymax>
		</bndbox>
	</object>
	<object>
		<name>pedestrian</name>
		<pose>Unspecified</pose>
		<truncated>0</truncated>
		<difficult>0</difficult>
		<occluded>0</occluded>
		<bndbox>
			<xmin>220</xmin>
			<xmax>230</xmax>
			<ymin>202</ymin>
			<ymax>231</ymax>
		</bndbox>
	</object>
	<object>
		<name>pedestrian</name>
		<pose>Unspecified</pose>
		<truncated>0</truncated>
		<difficult>0</difficult>
		<occluded>0</occluded>
		<bndbox>
			<xmin>222</xmin>
			<xmax>228</xmax>
			<ymin>203</ymin>
			<ymax>230</ymax>
		</bndbox>
	</object>
	<object>
		<name>pedestrian</name>
		<pose>Unspecified</pose>
		<truncated>0</truncated>
		<difficult>0</difficult>
		<occluded>0</occluded>
		<bndbox>
			<xmin>230</xmin>
			<xmax>240</xmax>
			<ymin>200</ymin>
			<ymax>237</ymax>
		</bndbox>
	</object>
	<object>
		<name>trafficLight-Red</name>
		<pose>Unspecified</pose>
		<truncated>0</truncated>
		<difficult>0</difficult>
		<occluded>0</occluded>
		<bndbox>
			<xmin>232</xmin>
			<xmax>239</xmax>
			<ymin>159</ymin>
			<ymax>182</ymax>
		</bndbox>
	</object>
	<object>
		<name>pedestrian</name>
		<pose>Unspecified</pose>
		<truncated>0</truncated>
		<difficult>0</difficult>
		<occluded>0</occluded>
		<bndbox>
			<xmin>243</xmin>
			<xmax>252</xmax>
			<ymin>200</ymin>
			<ymax>230</ymax>
		</bndbox>
	</object>
	<object>
		<name>biker</name>
		<pose>Unspecified</pose>
		<truncated>0</truncated>
		<difficult>0</difficult>
		<occluded>0</occluded>
		<bndbox>
			<xmin>268</xmin>
			<xmax>283</xmax>
			<ymin>202</ymin>
			<ymax>240</ymax>
		</bndbox>
	</object>
	<object>
		<name>car</name>
		<pose>Unspecified</pose>
		<truncated>0</truncated>
		<difficult>0</difficult>
		<occluded>0</occluded>
		<bndbox>
			<xmin>343</xmin>
			<xmax>417</xmax>
			<ymin>201</ymin>
			<ymax>235</ymax>
		</bndbox>
	</object>
</annotation>
