<annotation>
	<folder></folder>
	<filename>1478899965341426917_jpg.rf.3650bcb317a9a633339477a7ff6c2619.jpg</filename>
	<path>1478899965341426917_jpg.rf.3650bcb317a9a633339477a7ff6c2619.jpg</path>
	<source>
		<database>roboflow.ai</database>
	</source>
	<size>
		<width>416</width>
		<height>416</height>
		<depth>3</depth>
	</size>
	<segmented>0</segmented>
	<object>
		<name>trafficLight-RedLeft</name>
		<pose>Unspecified</pose>
		<truncated>0</truncated>
		<difficult>0</difficult>
		<occluded>0</occluded>
		<bndbox>
			<xmin>94</xmin>
			<xmax>99</xmax>
			<ymin>195</ymin>
			<ymax>208</ymax>
		</bndbox>
	</object>
	<object>
		<name>car</name>
		<pose>Unspecified</pose>
		<truncated>0</truncated>
		<difficult>0</difficult>
		<occluded>0</occluded>
		<bndbox>
			<xmin>2</xmin>
			<xmax>27</xmax>
			<ymin>218</ymin>
			<ymax>254</ymax>
		</bndbox>
	</object>
	<object>
		<name>car</name>
		<pose>Unspecified</pose>
		<truncated>0</truncated>
		<difficult>0</difficult>
		<occluded>0</occluded>
		<bndbox>
			<xmin>24</xmin>
			<xmax>58</xmax>
			<ymin>210</ymin>
			<ymax>231</ymax>
		</bndbox>
	</object>
	<object>
		<name>car</name>
		<pose>Unspecified</pose>
		<truncated>0</truncated>
		<difficult>0</difficult>
		<occluded>0</occluded>
		<bndbox>
			<xmin>141</xmin>
			<xmax>159</xmax>
			<ymin>210</ymin>
			<ymax>234</ymax>
		</bndbox>
	</object>
	<object>
		<name>car</name>
		<pose>Unspecified</pose>
		<truncated>0</truncated>
		<difficult>0</difficult>
		<occluded>0</occluded>
		<bndbox>
			<xmin>152</xmin>
			<xmax>190</xmax>
			<ymin>207</ymin>
			<ymax>251</ymax>
		</bndbox>
	</object>
	<object>
		<name>trafficLight-Red</name>
		<pose>Unspecified</pose>
		<truncated>0</truncated>
		<difficult>0</difficult>
		<occluded>0</occluded>
		<bndbox>
			<xmin>188</xmin>
			<xmax>194</xmax>
			<ymin>165</ymin>
			<ymax>180</ymax>
		</bndbox>
	</object>
	<object>
		<name>car</name>
		<pose>Unspecified</pose>
		<truncated>0</truncated>
		<difficult>0</difficult>
		<occluded>0</occluded>
		<bndbox>
			<xmin>266</xmin>
			<xmax>296</xmax>
			<ymin>198</ymin>
			<ymax>219</ymax>
		</bndbox>
	</object>
</annotation>
