<annotation>
	<folder></folder>
	<filename>1478896527319872231_jpg.rf.cafba5e00b2632c24d45e6ffa66997df.jpg</filename>
	<path>1478896527319872231_jpg.rf.cafba5e00b2632c24d45e6ffa66997df.jpg</path>
	<source>
		<database>roboflow.ai</database>
	</source>
	<size>
		<width>416</width>
		<height>416</height>
		<depth>3</depth>
	</size>
	<segmented>0</segmented>
	<object>
		<name>car</name>
		<pose>Unspecified</pose>
		<truncated>0</truncated>
		<difficult>0</difficult>
		<occluded>0</occluded>
		<bndbox>
			<xmin>114</xmin>
			<xmax>144</xmax>
			<ymin>212</ymin>
			<ymax>246</ymax>
		</bndbox>
	</object>
	<object>
		<name>car</name>
		<pose>Unspecified</pose>
		<truncated>0</truncated>
		<difficult>0</difficult>
		<occluded>0</occluded>
		<bndbox>
			<xmin>154</xmin>
			<xmax>166</xmax>
			<ymin>216</ymin>
			<ymax>233</ymax>
		</bndbox>
	</object>
	<object>
		<name>car</name>
		<pose>Unspecified</pose>
		<truncated>0</truncated>
		<difficult>0</difficult>
		<occluded>0</occluded>
		<bndbox>
			<xmin>176</xmin>
			<xmax>193</xmax>
			<ymin>216</ymin>
			<ymax>239</ymax>
		</bndbox>
	</object>
	<object>
		<name>car</name>
		<pose>Unspecified</pose>
		<truncated>0</truncated>
		<difficult>0</difficult>
		<occluded>0</occluded>
		<bndbox>
			<xmin>257</xmin>
			<xmax>310</xmax>
			<ymin>212</ymin>
			<ymax>262</ymax>
		</bndbox>
	</object>
</annotation>
